Metadata-Version: 1.1
Name: stapsdt
Version: 0.1.1
Summary: Create USDT probes and instrument your Python application dynamically
Home-page: https://github.com/sthima/python-stapsdt
Author: Matheus Marchini
Author-email: matheus@sthima.com
License: MIT
Keywords: usdt stapsdt systemtap sdt tracing probes instrumentation performance
Platform: UNKNOWN
Classifier: Development Status :: 4 - Beta
Classifier: Intended Audience :: Developers
Classifier: Topic :: Software Development :: Debuggers
Classifier: License :: OSI Approved :: MIT License
Classifier: Programming Language :: Python :: 3
Classifier: Programming Language :: Python :: 3.3
Classifier: Programming Language :: Python :: 3.4
Classifier: Programming Language :: Python :: 3.5
Classifier: Programming Language :: Python :: 3.6
